vortexdm/VortexDM.py
vortexdm/__init__.py
vortexdm/__main__.py
vortexdm/about.py
vortexdm/brain.py
vortexdm/cmdview.py
vortexdm/config.py
vortexdm/controller.py
vortexdm/dependency.py
vortexdm/downloaditem.py
vortexdm/iconsbase64.py
vortexdm/model.py
vortexdm/setting.py
vortexdm/systray.py
vortexdm/themes.py
vortexdm/tkview.py
vortexdm/update.py
vortexdm/utils.py
vortexdm/version.py
vortexdm/video.py
vortexdm/view.py
vortexdm/worker.py
vortexdm-2023.1.0.dist-info/LICENSE.md
vortexdm-2023.1.0.dist-info/METADATA
vortexdm-2023.1.0.dist-info/WHEEL
vortexdm-2023.1.0.dist-info/entry_points.txt
vortexdm-2023.1.0.dist-info/top_level.txt
vortexdm-2023.1.0.dist-info/RECORD
