Metadata-Version: 2.1
Name: vortexdm
Version: 2023.1.0
Summary: Vortex Download Manager
Home-page: https://github.com/Sixline/VortexDM 
Author: Mahmoud Elshahat
Maintainer: Sixline
Project-URL: Source, https://github.com/Sixline/VortexDM
Project-URL: Tracker, https://github.com/Sixline/VortexDM/issues
Project-URL: Releases, https://github.com/Sixline/VortexDM/releases
Keywords: vortexdm vdm firedm internet download manager youtube hls pycurl curl youtube-dl tkinter
Classifier: Programming Language :: Python :: 3.8
Classifier: Programming Language :: Python :: 3.9
Classifier: Programming Language :: Python :: 3.10
Classifier: Programming Language :: Python :: 3.11
Classifier: License :: OSI Approved :: GNU General Public License v3 or later (GPLv3+)
Classifier: Operating System :: OS Independent
Requires-Python: >=3.8
License-File: LICENSE.md
Requires-Dist: plyer
Requires-Dist: certifi
Requires-Dist: youtube-dl
Requires-Dist: yt-dlp
Requires-Dist: pycurl
Requires-Dist: Pillow (>=6.0.0)
Requires-Dist: pystray
Requires-Dist: awesometkinter (>=2021.6.4)
Requires-Dist: packaging
Requires-Dist: distro ; platform_system == "Linux"
